libsff/__init__.py
libsff/balloon.py
libsff/consts.py
libsff/document.py
libsff/errors.py
libsff-0.1.3.dist-info/LICENSE
libsff-0.1.3.dist-info/METADATA
libsff-0.1.3.dist-info/WHEEL
libsff-0.1.3.dist-info/top_level.txt
libsff-0.1.3.dist-info/RECORD
