Metadata-Version: 2.1
Name: libsff
Version: 0.1.3
Summary: A Pyhon parser for sff files.
Home-page: https://github.com/NandeMD/libsff
Author: NandeMD
License: GPL-3.0
Platform: UNKNOWN
Classifier: Intended Audience :: Developers
Classifier: Programming Language :: Python :: 3.8
Classifier: Programming Language :: Python :: 3.9
Classifier: Programming Language :: Python :: 3.10
Classifier: Operating System :: OS Independent
Classifier: Topic :: Software Development :: Libraries
Requires-Python: >=3.8.0
License-File: LICENSE
Requires-Dist: lxml (==4.9.1)
Requires-Dist: wheel
